aiowwlln/__init__.py
aiowwlln/client.py
aiowwlln/errors.py
aiowwlln/helpers/__init__.py
aiowwlln/helpers/geo.py
aiowwlln-2.0.5.dist-info/LICENSE
aiowwlln-2.0.5.dist-info/WHEEL
aiowwlln-2.0.5.dist-info/METADATA
aiowwlln-2.0.5.dist-info/RECORD
