Metadata-Version: 2.1
Name: aiowwlln
Version: 2.0.5
Summary: A simple Python API for the WWLLN
Home-page: https://github.com/bachya/aiowwlln
License: MIT
Author: Aaron Bach
Author-email: bachya1208@gmail.com
Requires-Python: >=3.6.1,<4.0.0
Classifier: License :: OSI Approved :: MIT License
Classifier: Programming Language :: Python
Classifier: Programming Language :: Python :: 3
Classifier: Programming Language :: Python :: 3.6
Classifier: Programming Language :: Python :: 3.7
Classifier: Programming Language :: Python :: 3.8
Classifier: Programming Language :: Python :: Implementation :: CPython
Classifier: Programming Language :: Python :: Implementation :: PyPy
Requires-Dist: aiocache (>=0.11.1,<0.12.0)
Requires-Dist: aiohttp (>=3.6.2,<4.0.0)
Requires-Dist: msgpack (>=0.6.2,<0.7.0)
Requires-Dist: ujson (>=1.35,<2.0)
Project-URL: Repository, https://github.com/bachya/aiowwlln
